LICENSE
LICENSE.txt
MANIFEST.in
README.md
README.rst
setup.cfg
setup.py
lazyearth/__init__.py
lazyearth/cloud.py
lazyearth/common.py
lazyearth/hidden.py
lazyearth/plot.py
lazyearth/readconfig_file.py
lazyearth/rsi.py
lazyearth/virtual.py
lazyearth/water.py
lazyearth.egg-info/PKG-INFO
lazyearth.egg-info/SOURCES.txt
lazyearth.egg-info/dependency_links.txt
lazyearth.egg-info/requires.txt
lazyearth.egg-info/top_level.txt
lazyearth/models/weights.h5
lazyearth/models/weights2.h5